libretificacaotjcore/__init__.py
libretificacaotjcore/database/__init__.py
libretificacaotjcore/database/arquivo_repository.py
libretificacaotjcore/database/certificado_repository.py
libretificacaotjcore/database/config_db.py
libretificacaotjcore/database/depentente_invalido_1210_repository.py
libretificacaotjcore/database/protocolo_repository.py
libretificacaotjcore/database/rubrica_repository.py
libretificacaotjcore/database/solicitacao_xml_repository.py
libretificacaotjcore/database/tempo_processo_repository.py
libretificacaotjcore/dtos/__init__.py
libretificacaotjcore/dtos/arquivo_dto.py
libretificacaotjcore/dtos/processo_dto.py
libretificacaotjcore/dtos/solicitacao_dto.py
libretificacaotjcore/enums/__init__.py
libretificacaotjcore/enums/e_eventos.py
libretificacaotjcore/enums/e_fase_retificacao.py
libretificacaotjcore/services/__init__.py
libretificacaotjcore/services/crypto_pass_service.py
libretificacaotjcore/services/file_service.py
libretificacaotjcore/services/rabbitmq_consumer.py
libretificacaotjcore/services/rabbitmq_publisher.py
libretificacaotjcore/services/request_servico_api.py
libretificacaotjcore/services/s3_service.py
libretificacaotjcore-0.1.85.dist-info/METADATA
libretificacaotjcore-0.1.85.dist-info/WHEEL
libretificacaotjcore-0.1.85.dist-info/top_level.txt
libretificacaotjcore-0.1.85.dist-info/RECORD
